plone.app.redirector-3.0.5-py3.13-nspkg.pth
plone/app/redirector/__init__.py
plone/app/redirector/browser.py
plone/app/redirector/configure.zcml
plone/app/redirector/interfaces.py
plone/app/redirector/policy.py
plone/app/redirector/storage.py
plone/app/redirector/subscribers.py
plone/app/redirector/testing.py
plone/app/redirector/tests/__init__.py
plone/app/redirector/tests/test_browser.py
plone/app/redirector/tests/test_events.py
plone/app/redirector/tests/test_performance.py
plone/app/redirector/tests/test_setup.py
plone/app/redirector/tests/test_storage.py
plone/app/redirector/tests/test_view.py
plone_app_redirector-3.0.5.dist-info/METADATA
plone_app_redirector-3.0.5.dist-info/WHEEL
plone_app_redirector-3.0.5.dist-info/namespace_packages.txt
plone_app_redirector-3.0.5.dist-info/top_level.txt
plone_app_redirector-3.0.5.dist-info/RECORD
